stadtradeln_data_manager/__init__.py
stadtradeln_data_manager/__main__.py
stadtradeln_data_manager/cli_utils.py
stadtradeln_data_tools/__init__.py
stadtradeln_data_tools/constants.py
stadtradeln_data_tools/dataset_clipper.py
stadtradeln_data_tools/dataset_downloader.py
stadtradeln_data_tools/dataset_extractor.py
stadtradeln_data_tools/linestring_conversion.py
stadtradeln_data_tools/pandas_importer.py
stadtradeln_data_tools/status.py
stadtradeln_data-0.0.2.dist-info/LICENSE
stadtradeln_data-0.0.2.dist-info/METADATA
stadtradeln_data-0.0.2.dist-info/WHEEL
stadtradeln_data-0.0.2.dist-info/entry_points.txt
stadtradeln_data-0.0.2.dist-info/top_level.txt
stadtradeln_data-0.0.2.dist-info/RECORD
