Metadata-Version: 2.1
Name: stadtradeln-data
Version: 0.0.2
Summary: A python package for downloading, extracting and clipping bicycle traffic count data from the STADTRADELN database
Home-page: https://github.com/Duam/stadtradeln-data
Author: Paul Daum
Author-email: paul.daum@posteo.de
License: MIT
Platform: UNKNOWN
Classifier: Programming Language :: Python :: 3
Classifier: Operating System :: OS Independent
Classifier: Topic :: Utilities
Classifier: License :: OSI Approved :: MIT License
Classifier: Intended Audience :: Science/Research
Classifier: Natural Language :: English
Classifier: Operating System :: Unix
Classifier: Topic :: Scientific/Engineering :: Information Analysis
Classifier: Typing :: Typed
Requires-Python: >=3.6
Requires-Dist: click
Requires-Dist: numpy
Requires-Dist: pandas
Requires-Dist: pytest
Requires-Dist: requests
Requires-Dist: tqdm
